{
   "displayName" : "Lore_Armor_Repair",
   "version" : "1.0",
   "buildNumber" : 2,
   "description" : "Lore Armor Repair\r\nDefault Values: 0.05 Per Ton Repair Time\r\nLore Armor: 0.01 Per Ton Repair Time\r\n\r\nIn novel lore armor could be hastily repaired and put back together in a Day, on the ground, In a mechbay euiped dropship there is no reason it makes no sense that it should take any longer.",
   "author" : "Weatherbee_A",
   "authorURL" : "",
   "defaultLoadOrder" : 10,
   "gameVersion" : "1.1.0",
   "manifest" : [
      "/Game/Objects/Mechs/_common/Equipment/FerroFibrousArmor.uasset",
      "/Game/Objects/Mechs/_common/Equipment/StandardArmor.uasset"
   ],
   "steamPublishedFileId" : 0,
   "steamLastSubmittedBuildNumber" : 0,
   "steamModVisibility" : "Private"
}